ADG4/__init__.py
ADG4/ad.py
ADG4/reverse.py
ADG4-0.1.1.dist-info/METADATA
ADG4-0.1.1.dist-info/WHEEL
ADG4-0.1.1.dist-info/top_level.txt
ADG4-0.1.1.dist-info/RECORD
