Metadata-Version: 2.1
Name: ADG4
Version: 0.1.1
Summary: ADG4 library
Home-page: https://github.com/CS107-gharvar4d/cs107-FinalProject
Author: Harvard Group 28
License: UNKNOWN
Platform: UNKNOWN
Requires-Python: >=3.6
Requires-Dist: numpy
Requires-Dist: pytest
Requires-Dist: pandas
